[{"authors":null,"categories":null,"content":"Hallo, ik ben Nele. In juni 2012 studeerde ik af als Master of Science in de pedagogische wetenschappen, afstudeerrichting orthopedagogiek, aan de KU Leuven. Vervolgens heb ik een eenjarig postgraduaat “Autisme en (rand-)normale begaafdheid, een bijzondere aanpak” aan de KHLim gevolgd. Verder voltooide ik in 2021 een vierjarige postgraduaat “Gedragstherapie bij kinderen en jongeren” aan de KU Leuven.\nDoor middel van regelmatige bijscholingen, super- en intervisie probeer ik mijn kennis en vaardigheden up-to-date te houden om mijn cliënten zo goed mogelijk verder te helpen. Ik ben verder ook lid van de Vlaamse Vereniging van Orthopedagogen (erkenningsnummer VVO1710093), en de Vlaamse Vereniging voor Gedragstherapie (VVGT). Mijn visumnummer (F.O.D.) als klinisch orthopedagoog is 288613.\nNa meer dan acht jaar op de afdeling voor jongvolwassenen met een autismespectrumstoornis (inclusief comorbide problematiek) van Medisch centrum Sint-Jozef, startte ik in 2021 als voltijds zelfstandig pedagoge. Naast mijn eigen praktijk, ben ik ook negen jaar werkzaam geweest in de Psychologie Praktijk te Hasselt, en twee jaar in Psychologenpraktijk Valkenburg.\n","date":-62135596800,"expirydate":-62135596800,"kind":"term","lang":"en","lastmod":-62135596800,"objectID":"8feebf363ee345318627d762b36e834b","permalink":"","publishdate":"0001-01-01T00:00:00Z","relpermalink":"","section":"authors","summary":"Hallo, ik ben Nele. In juni 2012 studeerde ik af als Master of Science in de pedagogische wetenschappen, afstudeerrichting orthopedagogiek, aan de KU Leuven. Vervolgens heb ik een eenjarig postgraduaat “Autisme en (rand-)normale begaafdheid, een bijzondere aanpak” aan de KHLim gevolgd.","tags":null,"title":"Nele Vanmuysen","type":"authors"}]